multidecoder/__init__.py
multidecoder/__main__.py
multidecoder/cli.py
multidecoder/core.py
multidecoder/output.py
multidecoder/decoders/__init__.py
multidecoder/decoders/basic.py
multidecoder/decoders/registry.py
text_multidecoder-0.1.1.dist-info/METADATA
text_multidecoder-0.1.1.dist-info/WHEEL
text_multidecoder-0.1.1.dist-info/entry_points.txt
text_multidecoder-0.1.1.dist-info/top_level.txt
text_multidecoder-0.1.1.dist-info/RECORD
