Metadata-Version: 2.4
Name: text-multidecoder
Version: 0.1.1
Summary: Recursively attempt to decode text
Requires-Python: >=3.12
Requires-Dist: chardet>=5.2.0
Requires-Dist: click>=8.3.1
